{
  "labId": "02-python-01-home-lab-python",
  "title": "Home Lab: Setting up Python on Your Desktop OS",
  "slug": "Understand, install, and verify operation of Python 2.7 and 3.x on your chosen Desktop OS: Windows, Linux, or Mac.",
  "time": "30",
  "byod": true,
  "tags": [
    {"title": "SDN"},
    {"title": "DNA"},
    {"title": "Networking"},
	{"title": "Python"}
  ],
  "related": [
    ],
  "files": [
    {"title": "Introduction",
     "file": "1.md"},
    {"title": "Related DevNet Learning Resources",
     "file": "2.md"},
    {"title": "Programming to Use DevNet Sandboxes and Other Devices",
     "file": "3.md"},
    {"title": "Verifying the Existing Python on Your PC",
     "file": "4.md"},
    {"title": "Installing and Verifying Python 2.7",
     "file": "5.md"},
    {"title": "Installing and Verifying Python 3.x",
     "file": "6.md"},
    {"title": "Running Python Programs",
     "file": "7.md"},
    {"title": "A Bit More about Python Commands",
     "file": "8.md"},
    {"title": "Summary", 
     "file": "9.md"}
  ],
  "authors": [
  	{"name": "Paul Zimmerman", "email": "pzimmerm@cisco.com"},
  	{"name": "Wendell Odom", "email": "wendell@certskills.com"}
  ],
  "active": true
}
